tarski/__init__.py
tarski/errors.py
tarski/fol.py
tarski/model.py
tarski/modules.py
tarski/theories.py
tarski/util.py
tarski/version.py
tarski/analysis/__init__.py
tarski/analysis/csp.py
tarski/analysis/csp_schema.py
tarski/benchmarks/__init__.py
tarski/benchmarks/blocksworld.py
tarski/benchmarks/counters.py
tarski/dl/__init__.py
tarski/dl/concepts.py
tarski/dl/errors.py
tarski/dl/factory.py
tarski/dl/features.py
tarski/evaluators/__init__.py
tarski/evaluators/simple.py
tarski/fstrips/__init__.py
tarski/fstrips/action.py
tarski/fstrips/derived.py
tarski/fstrips/errors.py
tarski/fstrips/fstrips.py
tarski/fstrips/ops.py
tarski/fstrips/problem.py
tarski/fstrips/representation.py
tarski/fstrips/visitors.py
tarski/fstrips/walker.py
tarski/fstrips/contingent/__init__.py
tarski/fstrips/contingent/errors.py
tarski/fstrips/contingent/problem.py
tarski/fstrips/contingent/sensor.py
tarski/fstrips/hybrid/__init__.py
tarski/fstrips/hybrid/differential_constraints.py
tarski/fstrips/hybrid/errors.py
tarski/fstrips/hybrid/problem.py
tarski/fstrips/hybrid/reaction.py
tarski/fstrips/manipulation/__init__.py
tarski/fstrips/manipulation/simplify.py
tarski/fstrips/manipulation/types.py
tarski/funcsym/__init__.py
tarski/grounding/__init__.py
tarski/grounding/common.py
tarski/grounding/errors.py
tarski/grounding/lp_grounding.py
tarski/grounding/naive_grounding.py
tarski/grounding/ops.py
tarski/grounding/naive/__init__.py
tarski/grounding/naive/constraints.py
tarski/grounding/naive/diff_constraints.py
tarski/grounding/naive/instantiation.py
tarski/grounding/naive/reactions.py
tarski/grounding/naive/sensors.py
tarski/grounding/naive/state_variables.py
tarski/io/__init__.py
tarski/io/common.py
tarski/io/fstrips.py
tarski/io/rddl.py
tarski/io/utils.py
tarski/io/_fstrips/__init__.py
tarski/io/_fstrips/common.py
tarski/io/_fstrips/reader.py
tarski/io/_fstrips/parser/__init__.py
tarski/io/_fstrips/parser/lexer.py
tarski/io/_fstrips/parser/listener.py
tarski/io/_fstrips/parser/parser.py
tarski_tmp-0.8.5.dist-info/licenses/LICENSE
tarski_tmp-0.8.5.dist-info/METADATA
tarski_tmp-0.8.5.dist-info/WHEEL
tarski_tmp-0.8.5.dist-info/top_level.txt
tarski_tmp-0.8.5.dist-info/RECORD
